{"P5": {"labels": ["FPGA"], "postTitle": "Vitis HLS \u7f16\u7a0b\u4f18\u8d28\u8d44\u6e90\u6536\u96c6", "postUrl": "post/Vitis-HLS-%E7%BC%96%E7%A8%8B%E4%BC%98%E8%B4%A8%E8%B5%84%E6%BA%90%E6%94%B6%E9%9B%86.html", "createdDate": "2024-05-18", "dateLabelColor": "#bc4c00"}, "P4": {"labels": ["FPGA"], "postTitle": " Vitis HLS CLI \u5b66\u4e60\u8bb0\u5f55", "postUrl": "post/-Vitis-HLS-CLI-%E5%AD%A6%E4%B9%A0%E8%AE%B0%E5%BD%95.html", "createdDate": "2024-05-11", "dateLabelColor": "#bc4c00"}, "P3": {"labels": ["FPGA", "Arch Linux"], "postTitle": "Run Vitis HLS Cli on Archlinux", "postUrl": "post/Run-Vitis-HLS-Cli-on-Archlinux.html", "createdDate": "2024-05-11", "dateLabelColor": "#bc4c00"}, "labelColorDict": {"Arch Linux": "#1793d1", "FPGA": "#ED6457", "\u6742\u8c08": "#91FD08"}}